psite_recommender/ALS.py
psite_recommender/Curve_inspection.py
psite_recommender/Embedding.py
psite_recommender/Extract_from_raw_data.py
psite_recommender/Heatmaps.py
psite_recommender/Neural_network_RS.py
psite_recommender/Preprocessing.py
psite_recommender/README.txt
psite_recommender/Recommender_system.py
psite_recommender-0.1.0.dist-info/LICENSE
psite_recommender-0.1.0.dist-info/WHEEL
psite_recommender-0.1.0.dist-info/METADATA
psite_recommender-0.1.0.dist-info/RECORD
